project_demo_2/__init__.py
project_demo_2-0.0.1.dist-info/METADATA
project_demo_2-0.0.1.dist-info/WHEEL
project_demo_2-0.0.1.dist-info/entry_points.txt
project_demo_2-0.0.1.dist-info/top_level.txt
project_demo_2-0.0.1.dist-info/RECORD
