Metadata-Version: 2.1
Name: project-demo-2
Version: 0.0.1
Summary: 吃枣药丸
Home-page: https://github.com/pypa/sampleproject
Author: test_author
Author-email: 18800102039@163.com
License: UNKNOWN
Platform: UNKNOWN
